odoo/addons/document_quick_access_folder_auto_classification/README.rst
odoo/addons/document_quick_access_folder_auto_classification/__init__.py
odoo/addons/document_quick_access_folder_auto_classification/__manifest__.py
odoo/addons/document_quick_access_folder_auto_classification/components/__init__.py
odoo/addons/document_quick_access_folder_auto_classification/components/document_quick_access_process.py
odoo/addons/document_quick_access_folder_auto_classification/data/edi_data.xml
odoo/addons/document_quick_access_folder_auto_classification/i18n/document_quick_access_folder_auto_classification.pot
odoo/addons/document_quick_access_folder_auto_classification/i18n/it.po
odoo/addons/document_quick_access_folder_auto_classification/models/__init__.py
odoo/addons/document_quick_access_folder_auto_classification/models/document_quick_access_rule.py
odoo/addons/document_quick_access_folder_auto_classification/readme/CONFIGURE.rst
odoo/addons/document_quick_access_folder_auto_classification/readme/CONTRIBUTORS.rst
odoo/addons/document_quick_access_folder_auto_classification/readme/DESCRIPTION.rst
odoo/addons/document_quick_access_folder_auto_classification/readme/USAGE.rst
odoo/addons/document_quick_access_folder_auto_classification/security/ir.model.access.csv
odoo/addons/document_quick_access_folder_auto_classification/security/security.xml
odoo/addons/document_quick_access_folder_auto_classification/static/description/icon.png
odoo/addons/document_quick_access_folder_auto_classification/static/description/icon.svg
odoo/addons/document_quick_access_folder_auto_classification/static/description/index.html
odoo/addons/document_quick_access_folder_auto_classification/tests/__init__.py
odoo/addons/document_quick_access_folder_auto_classification/tests/test_document_quick_access_auto_classification.py
odoo/addons/document_quick_access_folder_auto_classification/tests/test_file.pdf
odoo/addons/document_quick_access_folder_auto_classification/views/edi_exchange_record.xml
odoo_addon_document_quick_access_folder_auto_classification-16.0.1.0.1.dist-info/METADATA
odoo_addon_document_quick_access_folder_auto_classification-16.0.1.0.1.dist-info/WHEEL
odoo_addon_document_quick_access_folder_auto_classification-16.0.1.0.1.dist-info/top_level.txt
odoo_addon_document_quick_access_folder_auto_classification-16.0.1.0.1.dist-info/RECORD
