Metadata-Version: 2.1
Name: odoo-addon-document_quick_access_folder_auto_classification
Version: 16.0.1.0.1
Summary: Auto classification of Documents after reading a QR
Home-page: https://github.com/OCA/server-ux
Author: Creu Blanca,Odoo Community Association (OCA)
Author-email: support@odoo-community.org
License: AGPL-3
Classifier: Programming Language :: Python
Classifier: Framework :: Odoo
Classifier: Framework :: Odoo :: 16.0
Classifier: License :: OSI Approved :: GNU Affero General Public License v3
Requires-Python: >=3.10
Requires-Dist: odoo-addon-document-quick-access<16.1dev,>=16.0dev
Requires-Dist: odoo-addon-edi-oca<16.1dev,>=16.0dev
Requires-Dist: odoo<16.1dev,>=16.0a
Requires-Dist: pdf2image
Requires-Dist: pyzbar
